{
    "name" : "Râul Olt",
    "location" : [[45.261277555198916, 24.346712709548576]],
    "description" : "Oltenia este străjuită în nord de Carpații Meridionali, iar în vest, sud și est de ape curgătoare: Dunărea, respectiv Oltul. Oltul este unul din cele mai importante râuri din România. Acesta izvorăște din Carpații Orientali, mai precis din Munții Giurgeu, de acolo de unde aceștia intră în contact cu Munții Hășmaș prin Trecătoarea Oltului și se varsă în Dunăre în apropiere de Turnu Măgurele, la Islaz. ",
    "images" : "/static/images/raul_olt/raul_olt.jpg",
    "german_name" : "Kaprenburch",
    "german_description" : "Die Kaprenburch ist am besten",

    "french_name" : "Le Caprcoise",
    "french_description" : "Le Capricoise e tu un abeli' sdaddddasdasd"
}